activity_calendar_widget
