Metadata-Version: 2.1
Name: activity_calendar_widget
Version: 0.3
Summary: A PySide6 based activity calendar widget
Home-page: https://github.com/prmpsmart/activity_calendar_widget
Author: Miracle Apata
Author-email: prmpsmart@gmail.com
License: MIT
Project-URL: Bug Reports, https://github.com/prmpsmart/activity_calendar_widget/issues
Project-URL: Source, https://github.com/prmpsmart/activity_calendar_widget
Project-URL: Documentation, https://github.com/prmpsmart/activity_calendar_widget/blob/main/readme.md
Keywords: activity calendar widget python setuptools
Platform: any
Classifier: Development Status :: 3 - Alpha
Classifier: Intended Audience :: Developers
Classifier: License :: OSI Approved :: MIT License
Classifier: Programming Language :: Python :: 3
Classifier: Programming Language :: Python :: 3.6
Classifier: Programming Language :: Python :: 3.7
Classifier: Programming Language :: Python :: 3.8
Classifier: Programming Language :: Python :: 3.9
Classifier: Programming Language :: Python :: 3.10
Classifier: Programming Language :: Python :: 3.11
Classifier: Programming Language :: Python :: 3.12
Requires-Python: >=3.6
License-File: LICENSE
Requires-Dist: PySide6
